quantifin/__init__.py
quantifin/equity/Stock.py
quantifin/equity/__init__.py
quantifin/equity/test/__init__.py
quantifin/equity/test/test_cache.py
quantifin/equity/test/test_stock.py
quantifin/equity/test/test_valuation.py
quantifin/equity/valuation/__init__.py
quantifin/equity/valuation/valuation.py
quantifin/util/__init__.py
quantifin/util/greeks.py
quantifin/util/helper.py
quantifin/util/markets.py
quantifin/util/risk_free.py
quantifin/util/statistics.py
quantifin/util/test/__init__.py
quantifin/util/test/test_greeks.py
quantifin/util/test/test_risk_free.py
quantifin/util/test/test_statistics.py
quantifin/util/test/test_util.py
quantifin-0.0.42.dist-info/METADATA
quantifin-0.0.42.dist-info/WHEEL
quantifin-0.0.42.dist-info/top_level.txt
quantifin-0.0.42.dist-info/RECORD
