Metadata-Version: 2.1
Name: quantifin
Version: 0.0.42
Summary: Quant Finance Package
Home-page: https://github.com/yueda27/quantifin
Author: Yue Da Chua
Author-email: chua_yueda@hotmail.com
License: UNKNOWN
Platform: UNKNOWN
Classifier: Programming Language :: Python :: 3
Classifier: License :: OSI Approved :: MIT License
Classifier: Operating System :: OS Independent
Requires-Python: >=3.6
Requires-Dist: pandas
Requires-Dist: yahoofinancials (==1.6)
Requires-Dist: scipy
